balderhub/nextcloud/__init__.py
balderhub/nextcloud/_version.py
balderhub/nextcloud/lib/__init__.py
balderhub/nextcloud/lib/pages/__init__.py
balderhub/nextcloud/lib/pages/web/__init__.py
balderhub/nextcloud/lib/pages/web/base_page.py
balderhub/nextcloud/lib/pages/web/page_dashboard.py
balderhub/nextcloud/lib/pages/web/page_files.py
balderhub/nextcloud/lib/pages/web/page_login.py
balderhub/nextcloud/lib/pages/web/page_markdown_editor.py
balderhub/nextcloud/lib/scenario_features/__init__.py
balderhub/nextcloud/lib/scenario_features/is_nextcloud_server.py
balderhub/nextcloud/lib/scenario_features/is_nextcloud_v30_server.py
balderhub/nextcloud/lib/setup_features/__init__.py
balderhub/nextcloud/lib/utils/__init__.py
balderhub/nextcloud/lib/utils/helpers.py
balderhub/nextcloud/lib/utils/components/__init__.py
balderhub/nextcloud/lib/utils/components/web/__init__.py
balderhub/nextcloud/lib/utils/components/web/file_row_item.py
balderhub/nextcloud/lib/utils/components/web/files_list_table.py
balderhub/nextcloud/lib/utils/components/web/files_table_bulk_action.py
balderhub/nextcloud/lib/utils/components/web/menu_context.py
balderhub/nextcloud/lib/utils/components/web/menu_plus.py
balderhub/nextcloud/lib/utils/components/web/modal_copy_or_move_to.py
balderhub/nextcloud/lib/utils/components/web/modal_new_directory.py
balderhub/nextcloud/lib/utils/components/web/modal_new_text_file.py
balderhub/nextcloud/lib/utils/components/web/modal_pick_template.py
balderhub/nextcloud/lib/utils/components/web/modal_video.py
balderhub/nextcloud/lib/utils/components/web/modal_welcome.py
balderhub/nextcloud/scenarios/__init__.py
balderhub/nextcloud/setups/__init__.py
balderhub_nextcloud-0.0.1b0.dist-info/licenses/LICENSE
balderhub_nextcloud-0.0.1b0.dist-info/METADATA
balderhub_nextcloud-0.0.1b0.dist-info/WHEEL
balderhub_nextcloud-0.0.1b0.dist-info/top_level.txt
balderhub_nextcloud-0.0.1b0.dist-info/RECORD
