Metadata-Version: 2.4
Name: balderhub-nextcloud
Version: 0.0.1b0
Summary: balderhub-nextcloud: BalderHub project that provides different bindings to NextCloud Apps
Home-page: https://hub.balder.dev/projects/nextcloud
Author: Max Stahlschmidt
License: MIT
Project-URL: Source, https://github.com/balder-dev/balderhub-nextcloud/
Project-URL: Tracker, https://github.com/balder-dev/balderhub-nextcloud/issues
Keywords: test,systemtest,reusable,scenario,junit,balder
Platform: unix
Platform: linux
Platform: osx
Platform: cygwin
Platform: win32
Classifier: License :: OSI Approved :: MIT License
Classifier: Operating System :: MacOS :: MacOS X
Classifier: Operating System :: Microsoft :: Windows
Classifier: Operating System :: POSIX
Classifier: Intended Audience :: Developers
Classifier: Programming Language :: Python :: 3
Classifier: Programming Language :: Python :: 3 :: Only
Classifier: Programming Language :: Python :: 3.9
Classifier: Programming Language :: Python :: 3.10
Classifier: Topic :: Software Development :: Libraries
Classifier: Topic :: Software Development :: Testing
Classifier: Topic :: Utilities
Requires-Python: >=3.9
License-File: LICENSE
Requires-Dist: baldertest
Requires-Dist: balderhub-url
Requires-Dist: balderhub-html
Dynamic: license-file
